{
    "MissionStats": {
        "defined_type": "Build",
        "defined_subtype": "",
        "reward_currency": 0,
        "LEGOScore": 40,
        "reward_reputation": 100,
        "isChoiceReward": 0,
        "rewards": {
            "item1": {
                "reward_item1": 10165,
                "reward_item1_count": 1,
                "name": "Mega Brick Booster Pack",
                "displayName": "Mega Brick Booster Pack"
            },
            "item2": {
                "reward_item2": -1,
                "reward_item2_count": 0
            },
            "item3": {
                "reward_item3": -1,
                "reward_item3_count": 0
            },
            "item4": {
                "reward_item4": -1,
                "reward_item4_count": 0
            }
        },
        "isMission": 0,
        "repeatable": 0,
        "reward_maximagination": 0,
        "reward_maxhealth": 0,
        "reward_maxinventory": 0,
        "reward_bankinventory": null,
        "reward_emote": -1,
        "MissionText": {
            "description": "Visit 25 Properties that you have not previously visited, on any world.",
            "name": "The Visitor 1"
        }
    },
    "MissionTasks": {
        "id": 1199,
        "taskType": 30,
        "target": {
            "targetID": 1150,
            "targetNames": {}
        },
        "targetGroup": "1250,1350,1450,1151,1251",
        "iconID": 2928,
        "iconURL": "https://xiphoseer.github.io/lu-res/textures/ui/inventory/misc/m3608_treasure.png"
    }
}