{
    "MissionStats": {
        "defined_type": "Location",
        "defined_subtype": "Nimbus Station",
        "reward_currency": 0,
        "LEGOScore": 30,
        "reward_reputation": 0,
        "isChoiceReward": 0,
        "rewards": {
            "item1": {
                "reward_item1": -1,
                "reward_item1_count": 0
            },
            "item2": {
                "reward_item2": -1,
                "reward_item2_count": 0
            },
            "item3": {
                "reward_item3": -1,
                "reward_item3_count": 0
            },
            "item4": {
                "reward_item4": -1,
                "reward_item4_count": 0
            }
        },
        "isMission": 1,
        "repeatable": 0,
        "reward_maximagination": 0,
        "reward_maxhealth": 0,
        "reward_maxinventory": 0,
        "reward_bankinventory": null,
        "reward_emote": -1,
        "MissionText": {
            "description": "Open the Rank 1 Specialty Kit Package in your inventory, <font color='#FF7F00'>read the Rank 1 book</font>, and <font color='#FF7F00'>equip every piece of your Specialty Kit</font>.",
            "name": "Assembly Specialty Kit"
        }
    },
    "NPCComponent": {
        "NPCOfferComponentID": 174,
        "NPCAcceptComponentID": 174
    },
    "NPCOfferID": 6633,
    "NPCAcceptID": 6633,
    "NPCAcceptName": {
        "name": "NS Assembly Faction Vendor - Plaza",
        "displayName": "Meldric Steamvalve - Assembly Vendor"
    },
    "NPCOfferName": {
        "name": "NS Assembly Faction Vendor - Plaza",
        "displayName": "Meldric Steamvalve - Assembly Vendor"
    },
    "MissionTasks": {
        "id": 815,
        "taskType": 10,
        "target": {
            "targetID": null,
            "targetNames": {}
        },
        "targetGroup": "",
        "iconID": 3996,
        "iconURL": "https://xiphoseer.github.io/lu-res/textures/ui/inventory/misc/book_assembly.png"
    }
}