{
    "objectID": 9681,
    "itemInfo": {
        "name": "Test Pants Decal 0",
        "displayName": "Test Pants Decal 1",
        "type": "Loot",
        "description": "Test for Randall the Pants Hater",
        "internalNotes": "Test for Randall the Pants Hater"
    },
    "components": {
        "2": 9524,
        "11": 4721
    },
    "skillIDs": [],
    "objectSkills": {},
    "behaviorIDs": [],
    "stats": {},
    "itemComponent": {
        "subItems": null,
        "equipLocation": [
            "legs"
        ],
        "sellPrice": 0,
        "buyPrice": 0,
        "isKitPiece": 0,
        "rarity": 5,
        "itemComponent": 267296,
        "inLootTable": 0,
        "inVendor": 0,
        "stackSize": 1,
        "color": 1,
        "preconditions": [
            ""
        ],
        "isTwoHanded": 0,
        "altCurrencyType": null,
        "altCurrencyCost": null,
        "commendationCurrencyType": null,
        "commendationCurrencyCost": null,
        "equipLocationNames": [
            "Pants"
        ],
        "isWeapon": false
    },
    "overview": {},
    "proxySkillIDs": [],
    "proxySkills": {},
    "iconURL": "textures/ui/inventory/legs/m73200_21.png",
    "buyAndDrop": {
        "LootTableIndexes": [],
        "LootMatrixIndexes": {},
        "VendorComponents": [],
        "VendorIDs": [],
        "Vendors": [],
        "EnemyIDs": [],
        "Enemies": []
    },
    "earn": {}
}