{
    "objectID": 10316,
    "itemInfo": {
        "name": "DVD Order Model Pack",
        "displayName": "Surprise Model Pack",
        "type": "Loot",
        "description": "Double-click to open this pack of models!",
        "internalNotes": "Promo Item - Contains randomly selected small reward model"
    },
    "id": 10316,
    "comp_val": 44,
    "LootMatrixIndex": 416,
    "LootMatrixIndexInfo": {},
    "LootTableIndexes": [
        {
            "LootTableIndex": 296,
            "RarityTableIndex": 26,
            "percent": 100.0,
            "minToDrop": 1,
            "maxToDrop": 1,
            "size": 7,
            "names": {
                "LootTableIndex": "296",
                "Type": "Loot",
                "Name": "Vehicle Models"
            },
            "rarityTableInfo": {
                "4": {
                    "id": 89,
                    "randmax": 100.0,
                    "rarity": 4,
                    "chance": 100.0,
                    "weightedChance": 0,
                    "weightedChanceForSpecificItem": 0
                }
            },
            "rarityCount": {
                "1": 3,
                "2": 4,
                "3": 0,
                "4": 0,
                "5": 0
            },
            "total": 0
        }
    ],
    "components": {
        "2": 10162,
        "11": 5066,
        "53": 44
    },
    "iconURL": "textures/ui/inventory/presents/present_gray.png"
}