{
    "objectID": 2400,
    "itemInfo": {
        "name": "PR - BenTarrCat Scripted Mission Giver",
        "displayName": "PR - BenTarrCat Scripted Mission Giver",
        "type": "NPC",
        "description": "test",
        "internalNotes": null
    },
    "npcID": 2400,
    "components": {
        "1": 1777,
        "2": 2073,
        "5": 351,
        "16": null,
        "73": null
    },
    "iconURL": "https://xiphoseer.github.io/lu-res/textures/ui/missioncomics/wonderland/gnarled_forest/hud_icons/red_ninja.png",
    "isVendor": 0,
    "isMissionGiver": 0,
    "missions": {}
}