{
    "itemsList": [
        14127
    ],
    "items": {
        "14127": {
            "name": "Faction Token Bag - 200 tokens",
            "displayName": "Ultra-Mega Bag of Faction Tokens",
            "rarity": 1
        }
    },
    "itemComponentValues": [
        7004
    ],
    "rarityCount": {
        "1": 1,
        "2": 0,
        "3": 0,
        "4": 0,
        "5": 0
    },
    "byRarity": {
        "1": [
            14127
        ],
        "2": [],
        "3": [],
        "4": [],
        "5": []
    },
    "nameInfo": {
        "LootTableIndex": "680",
        "Type": "Loot",
        "Name": "Faction Token Bag - 200 tokens",
        "AlternateName": "Ultra-Mega Bag of Faction Tokens"
    }
}