{
    "itemsList": [
        9535,
        9538,
        9545,
        9546,
        9547,
        9548,
        9550,
        9553,
        9554,
        9555,
        9567,
        9590,
        10753,
        10757,
        10758,
        10759,
        10760,
        10761,
        10762,
        10764,
        10765,
        10766,
        10767,
        10769,
        10770,
        10771,
        8049,
        8050
    ],
    "items": {
        "8049": {
            "name": "Model Reward Lantern",
            "displayName": "Lantern Model",
            "rarity": 1
        },
        "8050": {
            "name": "Model Reward Shrine",
            "displayName": "Small Shrine Model",
            "rarity": 2
        },
        "9535": {
            "name": "Model Reward Pagoda",
            "displayName": "Pagoda Model",
            "rarity": 4
        },
        "9538": {
            "name": "Model Reward Small Arch",
            "displayName": "Small Arch Model",
            "rarity": 1
        },
        "9545": {
            "name": "Model Reward Fish Statue",
            "displayName": "Fish Statue Model",
            "rarity": 3
        },
        "9546": {
            "name": "Model Reward Ninja Fence Red",
            "displayName": "Red Ninja Fence Model",
            "rarity": 1
        },
        "9547": {
            "name": "Model Reward Ninja Fence Yellow",
            "displayName": "Yellow Ninja Fence Model",
            "rarity": 1
        },
        "9548": {
            "name": "Model Reward Ninja Fence Blue",
            "displayName": "Blue Ninja Fence Model",
            "rarity": 1
        },
        "9550": {
            "name": "Model Reward Temple 1",
            "displayName": "Temple Model 1",
            "rarity": 3
        },
        "9553": {
            "name": "Model Reward Zen Bamboo Medium",
            "displayName": "Zen Bamboo Medium Model",
            "rarity": 1
        },
        "9554": {
            "name": "Model Reward Zen Bamboo Small",
            "displayName": "Zen Bamboo Small Model",
            "rarity": 1
        },
        "9555": {
            "name": "Model Reward big door",
            "displayName": "Big Door Model",
            "rarity": 4
        },
        "9567": {
            "name": "Model Reward Pipestack",
            "displayName": "Pipestack Model",
            "rarity": 3
        },
        "9590": {
            "name": "Model Reward Anvil",
            "displayName": "Anvil Model",
            "rarity": 1
        },
        "10753": {
            "name": "Model Reward Fortress Cart",
            "displayName": "Fortress Cart Model",
            "rarity": 1
        },
        "10757": {
            "name": "Model Reward Fortress Elevator",
            "displayName": "Fortress Elevator Model",
            "rarity": 1
        },
        "10758": {
            "name": "Model Reward Fortress Gong",
            "displayName": "Fortress Gong Model",
            "rarity": 1
        },
        "10759": {
            "name": "Model Reward Fortress Inside Corner",
            "displayName": "Fortress Inside Corner Model",
            "rarity": 4
        },
        "10760": {
            "name": "Model Reward Fortress Lantern",
            "displayName": "Fortress Lantern Model",
            "rarity": 1
        },
        "10761": {
            "name": "Model Reward Fortress Large Outside Corner",
            "displayName": "Fortress Large Outside Corner Model",
            "rarity": 4
        },
        "10762": {
            "name": "Model Reward Fortress Large Wall",
            "displayName": "Fortress Large Wall Model",
            "rarity": 4
        },
        "10764": {
            "name": "Model Reward Fortress Pond",
            "displayName": "Fortress Pond Model",
            "rarity": 4
        },
        "10765": {
            "name": "Model Reward Fortress Ramp",
            "displayName": "Fortress Ramp Model",
            "rarity": 3
        },
        "10766": {
            "name": "Model Reward Fortress Small Outside Corner",
            "displayName": "Fortress Small Outside Corner Model",
            "rarity": 4
        },
        "10767": {
            "name": "Model Reward Fortress Small Wall",
            "displayName": "Fortress Small Wall Model",
            "rarity": 3
        },
        "10769": {
            "name": "Model Reward Fortress Wall Gate",
            "displayName": "Fortress Wall Gate Model",
            "rarity": 4
        },
        "10770": {
            "name": "Model Reward Fortress Wall Gate Sliding Door",
            "displayName": "Fortress Wall Gate Sliding Door Model",
            "rarity": 1
        },
        "10771": {
            "name": "Model Reward Fortress Watch Tower",
            "displayName": "Fortress Watch Tower Model",
            "rarity": 4
        }
    },
    "itemComponentValues": [
        3651,
        3652,
        4652,
        4568,
        4575,
        4576,
        4577,
        4578,
        4580,
        4583,
        4584,
        4585,
        4597,
        4620,
        5213,
        5217,
        5218,
        5219,
        5220,
        5221,
        5222,
        5224,
        5225,
        5226,
        5227,
        5229,
        5230,
        5231
    ],
    "rarityCount": {
        "1": 13,
        "2": 1,
        "3": 5,
        "4": 9,
        "5": 0
    },
    "byRarity": {
        "1": [
            9538,
            9546,
            9547,
            9548,
            9553,
            9554,
            9590,
            10753,
            10757,
            10758,
            10760,
            10770,
            8049
        ],
        "2": [
            8050
        ],
        "3": [
            9545,
            9550,
            9567,
            10765,
            10767
        ],
        "4": [
            9535,
            9555,
            10759,
            10761,
            10762,
            10764,
            10766,
            10769,
            10771
        ],
        "5": []
    },
    "nameInfo": {
        "LootTableIndex": "802",
        "Type": "Loot",
        "Name": "AG Model Vendor",
        "AlternateName": "AG Picnic Area"
    }
}