{
    "objectID": 3234,
    "itemInfo": {
        "name": "Old Man Sherland",
        "displayName": "Old Man Sherland",
        "type": "NPC",
        "description": "NP-Mission giver scene 3",
        "internalNotes": null
    },
    "npcID": 3234,
    "components": {
        "2": 2845,
        "3": 1731,
        "5": 424,
        "17": 25,
        "16": null,
        "73": null
    },
    "iconURL": "https://github.com/MasterTemple/lu_bot/blob/master/src/unknown.png?raw=true",
    "isVendor": 0,
    "isMissionGiver": 0,
    "missions": {}
}