{
    "objectID": 14325,
    "itemInfo": {
        "name": "Paradox Gear - Space Marauder - offhand proxy",
        "displayName": "Paradox Gear - Space Marauder - offhand proxy",
        "type": "Loot",
        "description": "",
        "internalNotes": ""
    },
    "components": {
        "2": 14014,
        "9": 0,
        "11": 7067
    },
    "skillIDs": [
        609
    ],
    "objectSkills": {
        "609": {
            "castOnType": 0,
            "AICombatWeight": 0,
            "behaviorID": 10520,
            "imaginationcost": 6,
            "cooldowngroup": 24,
            "cooldown": 5.0,
            "inNpcEditor": 0,
            "skillIcon": 3359,
            "imBonusUI": null,
            "lifeBonusUI": null,
            "armorBonusUI": null,
            "info": {
                "name": "Maelstrom Rocket 1",
                "rawDescription": "%(DamageCombo) 7 %(Description)Launches a rocket that does 7 damage",
                "damageCombo": " 7 ",
                "Description": "Launches a rocket that does 7 damage"
            }
        }
    },
    "behaviorIDs": [
        10520
    ],
    "stats": {
        "cooldown": 5.0,
        "cooldowngroup": 24
    },
    "itemComponent": {
        "subItems": null,
        "equipLocation": [
            "special_l"
        ],
        "sellPrice": 0,
        "buyPrice": 0,
        "isKitPiece": 1,
        "rarity": 4,
        "itemComponent": 0,
        "inLootTable": 1,
        "inVendor": 1,
        "stackSize": 1,
        "color": 10,
        "preconditions": null,
        "isTwoHanded": 0,
        "altCurrencyType": null,
        "altCurrencyCost": null,
        "commendationCurrencyType": null,
        "commendationCurrencyCost": null,
        "equipLocationNames": [
            "Left Hand"
        ],
        "isWeapon": false,
        "levelRequirement": 0
    },
    "overview": {
        "10520": {
            "hasChargeUp": false,
            "spawnsObject": false,
            "spawnsQuickbuild": false,
            "meleeAttack": true,
            "projectileAttack": true,
            "projectileAttackChargeUp": false,
            "damageComboArray": [
                1,
                1,
                1
            ],
            "chargeUpArmorRestore": [],
            "chargeUpImaginationRestore": [],
            "projectileLOTs": [
                9261
            ],
            "projectileInfo": {},
            "projectileDamageComboArray": [
                7
            ],
            "chargeUpCombo": 0,
            "allDamage": [
                7
            ],
            "attackTypes": [
                "Ranged",
                "Area of Effect"
            ]
        }
    },
    "proxySkillIDs": [],
    "proxySkills": {},
    "iconURL": "textures/ui/inventory/faction%20kits/spacemaurader_launcher_2.png",
    "buyAndDrop": {
        "LootTableIndexes": [],
        "LootMatrixIndexes": {},
        "VendorComponents": [],
        "VendorIDs": [],
        "Vendors": [],
        "EnemyIDs": [],
        "Enemies": []
    },
    "earn": {}
}