{
    "objectID": 7690,
    "itemInfo": {
        "name": "Test Breastplate of Scripting",
        "displayName": "Test Breastplate of Scripting",
        "type": "Loot",
        "description": "TEST Chest piece for scripting exploration",
        "internalNotes": "TEST Chest piece for scripting exploration"
    },
    "components": {
        "2": 7251,
        "5": 1028,
        "11": 3235,
        "72": 0
    },
    "skillIDs": [],
    "objectSkills": {},
    "behaviorIDs": [],
    "stats": {},
    "itemComponent": {
        "subItems": null,
        "equipLocation": [
            "clavicle"
        ],
        "sellPrice": 0,
        "buyPrice": 0,
        "isKitPiece": 1,
        "rarity": 5,
        "itemComponent": null,
        "inLootTable": 1,
        "inVendor": 1,
        "stackSize": 1,
        "color": 81,
        "preconditions": null,
        "isTwoHanded": 0,
        "altCurrencyType": null,
        "altCurrencyCost": null,
        "commendationCurrencyType": null,
        "commendationCurrencyCost": null,
        "equipLocationNames": [
            "Neck/Back"
        ],
        "isWeapon": false,
        "levelRequirement": 0
    },
    "overview": {},
    "proxySkillIDs": [],
    "proxySkills": {},
    "iconURL": "textures/ui/bricks/dds/m2587.png",
    "buyAndDrop": {
        "LootTableIndexes": [],
        "LootMatrixIndexes": {},
        "VendorComponents": [],
        "VendorIDs": [],
        "Vendors": [],
        "EnemyIDs": [],
        "Enemies": []
    },
    "earn": {}
}