{
    "objectID": 9859,
    "itemInfo": {
        "name": "AG Property Mission Giver 01",
        "displayName": "AG Property Mission Giver 01",
        "type": "NPC",
        "description": "__MG__AG Propery Battle",
        "internalNotes": null
    },
    "npcID": 9859,
    "components": {
        "2": 9691,
        "3": 1777,
        "5": 863,
        "7": 305,
        "17": 334,
        "35": 422,
        "73": 79,
        "16": null
    },
    "iconURL": "https://xiphoseer.github.io//lu-res/mesh//overhead_indicators//icon_mission_turn_in.png?raw=true",
    "isVendor": 0,
    "isMissionGiver": 1,
    "missions": {},
    "missionsList": []
}