{
    "objectID": 13155,
    "itemInfo": {
        "name": "Model Reward Skeleton Pet",
        "displayName": "Skeleton Pet Model",
        "type": "Loot",
        "description": "A model for your property!",
        "internalNotes": "Reward Model"
    },
    "components": {
        "2": 12936,
        "3": 6402,
        "11": 6525,
        "42": 0
    },
    "skillIDs": [],
    "objectSkills": {},
    "behaviorIDs": [],
    "stats": {},
    "itemComponent": {
        "subItems": null,
        "equipLocation": [
            "Extra_1"
        ],
        "sellPrice": 10,
        "buyPrice": 100,
        "isKitPiece": 0,
        "rarity": 2,
        "itemComponent": null,
        "inLootTable": 1,
        "inVendor": 0,
        "stackSize": 10,
        "color": null,
        "preconditions": [
            "62|26"
        ],
        "isTwoHanded": 0,
        "altCurrencyType": null,
        "altCurrencyCost": null,
        "commendationCurrencyType": null,
        "commendationCurrencyCost": null,
        "equipLocationNames": [],
        "isWeapon": false
    },
    "overview": {},
    "proxySkillIDs": [],
    "proxySkills": {},
    "iconURL": "textures/ui/inventory/models/rew_skeleton_pet.png",
    "buyAndDrop": {
        "LootTableIndexes": [
            602
        ],
        "LootMatrixIndexes": {
            "656": {
                "LootMatrixIndex": 656,
                "LootTableIndex": 602,
                "RarityTableIndex": 4,
                "percent": 80.0,
                "minToDrop": 1,
                "maxToDrop": 2,
                "DestructibleComponent": {},
                "rarityTableInfo": {
                    "1": {
                        "id": 17,
                        "randmax": 75.0,
                        "rarity": 1,
                        "chance": 75.0
                    },
                    "2": {
                        "id": 18,
                        "randmax": 90.0,
                        "rarity": 2,
                        "chance": 15.0
                    },
                    "4": {
                        "id": 19,
                        "randmax": 100.0,
                        "rarity": 4,
                        "chance": 2.0
                    },
                    "3": {
                        "id": 22,
                        "randmax": 98.0,
                        "rarity": 3,
                        "chance": 8.0
                    }
                },
                "rarityCount": {
                    "1": 0,
                    "2": 7,
                    "3": 4,
                    "4": 0,
                    "5": 0
                },
                "inNpcEditor": 0,
                "overallChance": {
                    "percent": 1.7143,
                    "howManyToKill": 49
                },
                "LootTableIndexItems": 11,
                "PackageComponent": {
                    "656": {
                        "name": "Nexus Force Supply Crate",
                        "displayName": "Nexus Force Supply Crate"
                    }
                },
                "ActivityComponent": []
            }
        },
        "VendorComponents": [],
        "VendorIDs": [],
        "Vendors": [],
        "EnemyIDs": [],
        "Enemies": []
    },
    "earn": {}
}